pyamda/__init__.py
pyamda/__main__.py
pyamda/bools.py
pyamda/clss.py
pyamda/core.py
pyamda/dicts.py
pyamda/iters.py
pyamda/lists.py
pyamda/maths.py
pyamda/py.typed
pyamda/strs.py
pyamda-2.11.0.dist-info/LICENSE
pyamda-2.11.0.dist-info/METADATA
pyamda-2.11.0.dist-info/WHEEL
pyamda-2.11.0.dist-info/top_level.txt
pyamda-2.11.0.dist-info/RECORD
