Metadata-Version: 2.1
Name: pyamda
Version: 2.11.0
Summary: The simplest, type-iest functional utils for Python
Author-email: ekewn <ellis.coon@gmail.com>
License:                     GNU GENERAL PUBLIC LICENSE
Keywords: functional,fp,ramda,pipeline,utilities,utils,pipeline oriented
Classifier: Programming Language :: Python :: 3
Requires-Python: >=3.12
License-File: LICENSE
